README.md
setup.cfg
setup.py
api.video.egg-info/PKG-INFO
api.video.egg-info/SOURCES.txt
api.video.egg-info/dependency_links.txt
api.video.egg-info/requires.txt
api.video.egg-info/top_level.txt
apivideo/__init__.py
apivideo/api_client.py
apivideo/auth_api_client.py
apivideo/configuration.py
apivideo/endpoint.py
apivideo/exceptions.py
apivideo/model_utils.py
apivideo/rest.py
apivideo/api/__init__.py
apivideo/api/analytics_api.py
apivideo/api/captions_api.py
apivideo/api/chapters_api.py
apivideo/api/live_streams_api.py
apivideo/api/player_themes_api.py
apivideo/api/summaries_api.py
apivideo/api/tags_api.py
apivideo/api/upload_tokens_api.py
apivideo/api/videos_api.py
apivideo/api/watermarks_api.py
apivideo/api/webhooks_api.py
apivideo/apis/__init__.py
apivideo/model/__init__.py
apivideo/model/access_token.py
apivideo/model/additional_bad_request_errors.py
apivideo/model/analytics_aggregated_metrics_response.py
apivideo/model/analytics_aggregated_metrics_response_context.py
apivideo/model/analytics_aggregated_metrics_response_context_timeframe.py
apivideo/model/analytics_data.py
apivideo/model/analytics_metrics_breakdown_response.py
apivideo/model/analytics_metrics_breakdown_response_context.py
apivideo/model/analytics_metrics_breakdown_response_data.py
apivideo/model/analytics_metrics_over_time_response.py
apivideo/model/analytics_metrics_over_time_response_context.py
apivideo/model/analytics_metrics_over_time_response_data.py
apivideo/model/analytics_plays400_error.py
apivideo/model/analytics_plays_response.py
apivideo/model/authenticate_payload.py
apivideo/model/bad_request.py
apivideo/model/bytes_range.py
apivideo/model/caption.py
apivideo/model/captions_list_response.py
apivideo/model/captions_update_payload.py
apivideo/model/chapter.py
apivideo/model/chapters_list_response.py
apivideo/model/conflict_error.py
apivideo/model/discarded_video_update_payload.py
apivideo/model/filter_by.py
apivideo/model/filter_by1.py
apivideo/model/filter_by2.py
apivideo/model/link.py
apivideo/model/list_tags_response.py
apivideo/model/list_tags_response_data.py
apivideo/model/live_stream.py
apivideo/model/live_stream_assets.py
