Metadata-Version: 2.1
Name: api.video
Version: 1.4.7
Summary: api.video Python API client
Home-page: https://github.com/apivideo/api.video-python-client
Author: api.video ecosystem team
Author-email: ecosystem@api.video
License: MIT
Keywords: api.video,sdk,api client,video,live,hls
Platform: UNKNOWN
Requires-Python: >=3.6
